rahhscidow/__init__.py
rahhscidow/rahhscidow.py
rahhscidow-1.2.3.2.dist-info/METADATA
rahhscidow-1.2.3.2.dist-info/WHEEL
rahhscidow-1.2.3.2.dist-info/entry_points.txt
rahhscidow-1.2.3.2.dist-info/top_level.txt
rahhscidow-1.2.3.2.dist-info/RECORD
