Metadata-Version: 2.1
Name: rahhscidow
Version: 1.2.3.2
Summary: A Scihub paper downloader.
Requires-Python: >=3.11
